{"title":"第10回ちゅんま関東リーグ 2回戦 A卓","player":["赤塚 修","土屋 政士","根本 卓也","左 永"],"qijia":0,"log":[
[{"qipai":{"quanfeng":0,"jushu":0,"zuoci":[0,1,2,3],"defen":[0,0,0,0],"shoupai":["m566p2367s789z236","m4p1124s125669z34","m7889p13559z1135","m127p25667s27z357"]}},{"zimo":{"l":0,"p":"m2"}},{"dapai":{"l":0,"p":"z3"}},{"zimo":{"l":1,"p":"z7"}},{"dapai":{"l":1,"p":"z3"}},{"zimo":{"l":2,"p":"m1"}},{"dapai":{"l":2,"p":"z3"}},{"zimo":{"l":3,"p":"s5"}},{"dapai":{"l":3,"p":"z3"}},{"zimo":{"l":0,"p":"s4"}},{"dapai":{"l":0,"p":"z2"}},{"zimo":{"l":1,"p":"s4"}},{"dapai":{"l":1,"p":"z4"}},{"zimo":{"l":2,"p":"s9"}},{"dapai":{"l":2,"p":"z5"}},{"zimo":{"l":3,"p":"m3"}},{"dapai":{"l":3,"p":"z5"}},{"zimo":{"l":0,"p":"p4"}},{"dapai":{"l":0,"p":"z6"}},{"zimo":{"l":1,"p":"s1"}},{"dapai":{"l":1,"p":"z7"}},{"zimo":{"l":2,"p":"s3"}},{"dapai":{"l":2,"p":"p5"}},{"zimo":{"l":3,"p":"p6"}},{"dapai":{"l":3,"p":"z7"}},{"zimo":{"l":0,"p":"s9"}},{"dapai":{"l":0,"p":"m2"}},{"zimo":{"l":1,"p":"s5"}},{"dapai":{"l":1,"p":"m4"}},{"zimo":{"l":2,"p":"m9"}},{"dapai":{"l":2,"p":"p5"}},{"zimo":{"l":3,"p":"p8"}},{"dapai":{"l":3,"p":"s2"}},{"zimo":{"l":0,"p":"z1"}},{"dapai":{"l":0,"p":"z1_"}},{"fulou":{"l":2,"m":"z111="}},{"dapai":{"l":2,"p":"s3"}},{"zimo":{"l":3,"p":"s3"}},{"dapai":{"l":3,"p":"p2"}},{"zimo":{"l":0,"p":"z2"}},{"dapai":{"l":0,"p":"z2_"}},{"zimo":{"l":1,"p":"s6"}},{"dapai":{"l":1,"p":"s9"}},{"zimo":{"l":2,"p":"p8"}},{"dapai":{"l":2,"p":"m1"}},{"zimo":{"l":3,"p":"m2"}},{"dapai":{"l":3,"p":"m2_"}},{"zimo":{"l":0,"p":"z1"}},{"dapai":{"l":0,"p":"z1_"}},{"zimo":{"l":1,"p":"m6"}},{"dapai":{"l":1,"p":"m6_"}},{"zimo":{"l":2,"p":"p8"}},{"dapai":{"l":2,"p":"p8_"}},{"zimo":{"l":3,"p":"s5"}},{"dapai":{"l":3,"p":"s3"}},{"zimo":{"l":0,"p":"p8"}},{"dapai":{"l":0,"p":"m6"}},{"zimo":{"l":1,"p":"s1"}},{"dapai":{"l":1,"p":"s2"}},{"zimo":{"l":2,"p":"p7"}},{"dapai":{"l":2,"p":"s9"}},{"zimo":{"l":3,"p":"m8"}},{"dapai":{"l":3,"p":"s5"}},{"zimo":{"l":0,"p":"m3"}},{"dapai":{"l":0,"p":"s9"}},{"zimo":{"l":1,"p":"m4"}},{"dapai":{"l":1,"p":"m4_"}},{"zimo":{"l":2,"p":"p2"}},{"dapai":{"l":2,"p":"m8"}},{"zimo":{"l":3,"p":"m1"}},{"dapai":{"l":3,"p":"m1_"}},{"zimo":{"l":0,"p":"z4"}},{"dapai":{"l":0,"p":"z4_"}},{"zimo":{"l":1,"p":"p3"}},{"dapai":{"l":1,"p":"s4"}},{"zimo":{"l":2,"p":"z4"}},{"dapai":{"l":2,"p":"z4_"}},{"zimo":{"l":3,"p":"s4"}},{"dapai":{"l":3,"p":"p5"}},{"zimo":{"l":0,"p":"m3"}},{"dapai":{"l":0,"p":"s4"}},{"zimo":{"l":1,"p":"z5"}},{"dapai":{"l":1,"p":"z5_"}},{"zimo":{"l":2,"p":"s7"}},{"dapai":{"l":2,"p":"s7_"}},{"zimo":{"l":3,"p":"s8"}},{"dapai":{"l":3,"p":"s4"}},{"zimo":{"l":0,"p":"z6"}},{"dapai":{"l":0,"p":"z6_"}},{"zimo":{"l":1,"p":"z7"}},{"dapai":{"l":1,"p":"z7_"}},{"zimo":{"l":2,"p":"m7"}},{"dapai":{"l":2,"p":"m7_"}},{"hule":{"chongjia":2,"l":0,"shoupai":"m3356p234678s789m7_","zongfen":10,"fanzhong":[{"name_zh":"三色三步高","fenshu":6},{"name_zh":"门前清","fenshu":2},{"name_zh":"平和","fenshu":2}],"fenpei":[34,-8,-18,-8]}}],
[{"qipai":{"quanfeng":0,"jushu":1,"zuoci":[1,2,3,0],"defen":[-8,-18,-8,34],"shoupai":["m16p1366s23459z34","m3457p589s1899z57","m8p59s135679z2335","m13789p18s36z1224"]}},{"zimo":{"l":0,"p":"s2"}},{"dapai":{"l":0,"p":"z4"}},{"zimo":{"l":1,"p":"p7"}},{"dapai":{"l":1,"p":"z5"}},{"zimo":{"l":2,"p":"m6"}},{"dapai":{"l":2,"p":"z5"}},{"zimo":{"l":3,"p":"s7"}},{"dapai":{"l":3,"p":"p1"}},{"zimo":{"l":0,"p":"z4"}},{"dapai":{"l":0,"p":"z4_"}},{"zimo":{"l":1,"p":"p2"}},{"dapai":{"l":1,"p":"z7"}},{"zimo":{"l":2,"p":"z3"}},{"dapai":{"l":2,"p":"p9"}},{"zimo":{"l":3,"p":"p6"}},{"dapai":{"l":3,"p":"z4"}},{"zimo":{"l":0,"p":"z1"}},{"dapai":{"l":0,"p":"z1_"}},{"zimo":{"l":1,"p":"s4"}},{"dapai":{"l":1,"p":"p2"}},{"zimo":{"l":2,"p":"p2"}},{"dapai":{"l":2,"p":"p2_"}},{"zimo":{"l":3,"p":"p6"}},{"dapai":{"l":3,"p":"z1"}},{"zimo":{"l":0,"p":"s7"}},{"dapai":{"l":0,"p":"z3"}},{"zimo":{"l":1,"p":"p1"}},{"dapai":{"l":1,"p":"p1_"}},{"zimo":{"l":2,"p":"p2"}},{"dapai":{"l":2,"p":"p2_"}},{"zimo":{"l":3,"p":"m9"}},{"dapai":{"l":3,"p":"p6"}},{"zimo":{"l":0,"p":"z7"}},{"dapai":{"l":0,"p":"z7_"}},{"zimo":{"l":1,"p":"m1"}},{"dapai":{"l":1,"p":"s1"}},{"zimo":{"l":2,"p":"m6"}},{"dapai":{"l":2,"p":"p5"}},{"zimo":{"l":3,"p":"s5"}},{"dapai":{"l":3,"p":"s3"}},{"zimo":{"l":0,"p":"z1"}},{"dapai":{"l":0,"p":"z1_"}},{"zimo":{"l":1,"p":"z2"}},{"dapai":{"l":1,"p":"z2_"}},{"zimo":{"l":2,"p":"m3"}},{"dapai":{"l":2,"p":"m3_"}},{"zimo":{"l":3,"p":"m3"}},{"dapai":{"l":3,"p":"m9"}},{"zimo":{"l":0,"p":"z6"}},{"dapai":{"l":0,"p":"z6_"}},{"zimo":{"l":1,"p":"p2"}},{"dapai":{"l":1,"p":"p2_"}},{"zimo":{"l":2,"p":"p8"}},{"dapai":{"l":2,"p":"p8_"}},{"zimo":{"l":3,"p":"z7"}},{"dapai":{"l":3,"p":"z7_"}},{"zimo":{"l":0,"p":"m4"}},{"dapai":{"l":0,"p":"p1"}},{"zimo":{"l":1,"p":"p8"}},{"dapai":{"l":1,"p":"s4"}},{"fulou":{"l":2,"m":"s4-56"}},{"dapai":{"l":2,"p":"m8"}},{"zimo":{"l":3,"p":"m4"}},{"dapai":{"l":3,"p":"m4_"}},{"zimo":{"l":0,"p":"m8"}},{"dapai":{"l":0,"p":"m1"}},{"zimo":{"l":1,"p":"s4"}},{"dapai":{"l":1,"p":"m1"}},{"zimo":{"l":2,"p":"z6"}},{"dapai":{"l":2,"p":"z6_"}},{"zimo":{"l":3,"p":"s4"}},{"dapai":{"l":3,"p":"s4_"}},{"zimo":{"l":0,"p":"p4"}},{"dapai":{"l":0,"p":"p3"}},{"zimo":{"l":1,"p":"s2"}},{"dapai":{"l":1,"p":"p8"}},{"zimo":{"l":2,"p":"s8"}},{"dapai":{"l":2,"p":"z2"}},{"fulou":{"l":3,"m":"z222-"}},{"dapai":{"l":3,"p":"m1"}},{"zimo":{"l":0,"p":"p4"}},{"dapai":{"l":0,"p":"p4_"}},{"zimo":{"l":1,"p":"s8"}},{"dapai":{"l":1,"p":"p5"}},{"zimo":{"l":2,"p":"s1"}},{"dapai":{"l":2,"p":"s1_"}},{"zimo":{"l":3,"p":"s7"}},{"dapai":{"l":3,"p":"s7"}},{"zimo":{"l":0,"p":"m7"}},{"dapai":{"l":0,"p":"m4"}},{"zimo":{"l":1,"p":"s1"}},{"dapai":{"l":1,"p":"m7"}},{"zimo":{"l":2,"p":"p4"}},{"dapai":{"l":2,"p":"p4_"}},{"zimo":{"l":3,"p":"m6"}},{"dapai":{"l":3,"p":"m6_"}},{"zimo":{"l":0,"p":"m5"}},{"dapai":{"l":0,"p":"m8"}},{"zimo":{"l":1,"p":"p3"}},{"dapai":{"l":1,"p":"p3_"}},{"zimo":{"l":2,"p":"z5"}},{"dapai":{"l":2,"p":"z5_"}},{"zimo":{"l":3,"p":"m8"}},{"dapai":{"l":3,"p":"m8_"}},{"zimo":{"l":0,"p":"m9"}},{"dapai":{"l":0,"p":"m9_"}},{"zimo":{"l":1,"p":"z6"}},{"dapai":{"l":1,"p":"z6_"}},{"zimo":{"l":2,"p":"z7"}},{"dapai":{"l":2,"p":"z7_"}},{"zimo":{"l":3,"p":"m2"}},{"dapai":{"l":3,"p":"m2_"}},{"zimo":{"l":0,"p":"z5"}},{"dapai":{"l":0,"p":"z5_"}},{"zimo":{"l":1,"p":"s5"}},{"dapai":{"l":1,"p":"m3"}},{"zimo":{"l":2,"p":"z6"}},{"dapai":{"l":2,"p":"z6_"}},{"zimo":{"l":3,"p":"p7"}},{"hule":{"chongjia":null,"l":3,"shoupai":"m33789p68s567p7,z222-","zongfen":9,"fanzhong":[{"name_zh":"三色三步高","fenshu":6},{"name_zh":"幺九刻","fenshu":1},{"name_zh":"坎张","fenshu":1},{"name_zh":"自摸","fenshu":1}],"fenpei":[-17,-17,-17,51]}}],
[{"qipai":{"quanfeng":0,"jushu":2,"zuoci":[2,3,0,1],"defen":[-35,-25,85,-25],"shoupai":["m1147799p14677z6","m144p3s1445589z77","m2455p4789s35z223","m6p23579s6788z455"]}},{"zimo":{"l":0,"p":"z2"}},{"dapai":{"l":0,"p":"z2_"}},{"zimo":{"l":1,"p":"s1"}},{"dapai":{"l":1,"p":"m1"}},{"fulou":{"l":0,"m":"m111+"}},{"dapai":{"l":0,"p":"z6"}},{"zimo":{"l":1,"p":"m6"}},{"dapai":{"l":1,"p":"m6_"}},{"zimo":{"l":2,"p":"m7"}},{"dapai":{"l":2,"p":"z3"}},{"zimo":{"l":3,"p":"m3"}},{"dapai":{"l":3,"p":"z4"}},{"zimo":{"l":0,"p":"p2"}},{"dapai":{"l":0,"p":"m4"}},{"zimo":{"l":1,"p":"m2"}},{"dapai":{"l":1,"p":"p3"}},{"zimo":{"l":2,"p":"p9"}},{"dapai":{"l":2,"p":"z2"}},{"zimo":{"l":3,"p":"m2"}},{"dapai":{"l":3,"p":"s8"}},{"zimo":{"l":0,"p":"z4"}},{"dapai":{"l":0,"p":"z4_"}},{"zimo":{"l":1,"p":"z2"}},{"dapai":{"l":1,"p":"z2_"}},{"zimo":{"l":2,"p":"s1"}},{"dapai":{"l":2,"p":"z2"}},{"zimo":{"l":3,"p":"m5"}},{"dapai":{"l":3,"p":"z5"}},{"zimo":{"l":0,"p":"z6"}},{"dapai":{"l":0,"p":"z6_"}},{"zimo":{"l":1,"p":"s2"}},{"dapai":{"l":1,"p":"m2"}},{"zimo":{"l":2,"p":"s9"}},{"dapai":{"l":2,"p":"s9_"}},{"zimo":{"l":3,"p":"p2"}},{"dapai":{"l":3,"p":"z5"}},{"zimo":{"l":0,"p":"m3"}},{"dapai":{"l":0,"p":"m3_"}},{"zimo":{"l":1,"p":"s6"}},{"dapai":{"l":1,"p":"m4"}},{"zimo":{"l":2,"p":"p6"}},{"dapai":{"l":2,"p":"m2"}},{"zimo":{"l":3,"p":"s8"}},{"dapai":{"l":3,"p":"s8_"}},{"zimo":{"l":0,"p":"s2"}},{"dapai":{"l":0,"p":"s2_"}},{"zimo":{"l":1,"p":"s2"}},{"dapai":{"l":1,"p":"m4"}},{"zimo":{"l":2,"p":"p8"}},{"dapai":{"l":2,"p":"m5"}},{"zimo":{"l":3,"p":"z1"}},{"dapai":{"l":3,"p":"z1_"}},{"zimo":{"l":0,"p":"p8"}},{"dapai":{"l":0,"p":"p1"}},{"zimo":{"l":1,"p":"p1"}},{"dapai":{"l":1,"p":"p1_"}},{"zimo":{"l":2,"p":"m9"}},{"dapai":{"l":2,"p":"p8"}},{"fulou":{"l":3,"m":"p78-9"}},{"dapai":{"l":3,"p":"m3"}},{"zimo":{"l":0,"p":"m5"}},{"dapai":{"l":0,"p":"m5_"}},{"zimo":{"l":1,"p":"z5"}},{"dapai":{"l":1,"p":"z5_"}},{"zimo":{"l":2,"p":"s3"}},{"dapai":{"l":2,"p":"s3"}},{"zimo":{"l":3,"p":"m6"}},{"dapai":{"l":3,"p":"m2"}},{"zimo":{"l":0,"p":"s6"}},{"dapai":{"l":0,"p":"p8"}},{"zimo":{"l":1,"p":"s3"}},{"dapai":{"l":1,"p":"s8"}},{"zimo":{"l":2,"p":"s7"}},{"dapai":{"l":2,"p":"s1"}},{"fulou":{"l":1,"m":"s111+"}},{"dapai":{"l":1,"p":"s9"}},{"zimo":{"l":2,"p":"z1"}},{"dapai":{"l":2,"p":"z1_"}},{"zimo":{"l":3,"p":"s4"}},{"dapai":{"l":3,"p":"m6"}},{"zimo":{"l":0,"p":"m1"}},{"gang":{"l":0,"m":"m111+1"}},{"zimo":{"l":0,"p":"m3"}},{"dapai":{"l":0,"p":"m3_"}},{"zimo":{"l":1,"p":"p5"}},{"dapai":{"l":1,"p":"p5_"}},{"zimo":{"l":2,"p":"s9"}},{"dapai":{"l":2,"p":"s9_"}},{"zimo":{"l":3,"p":"z3"}},{"dapai":{"l":3,"p":"z3_"}},{"zimo":{"l":0,"p":"p3"}},{"dapai":{"l":0,"p":"s6"}},{"fulou":{"l":1,"m":"s456-"}},{"dapai":{"l":1,"p":"s2"}},{"zimo":{"l":2,"p":"p5"}},{"dapai":{"l":2,"p":"m9"}},{"fulou":{"l":0,"m":"m999="}},{"dapai":{"l":0,"p":"p6"}},{"zimo":{"l":1,"p":"z4"}},{"dapai":{"l":1,"p":"z4_"}},{"zimo":{"l":2,"p":"p4"}},{"dapai":{"l":2,"p":"p9"}},{"zimo":{"l":3,"p":"m2"}},{"dapai":{"l":3,"p":"m2_"}},{"zimo":{"l":0,"p":"s6"}},{"dapai":{"l":0,"p":"s6_"}},{"zimo":{"l":1,"p":"p3"}},{"dapai":{"l":1,"p":"p3_"}},{"zimo":{"l":2,"p":"s5"}},{"dapai":{"l":2,"p":"s5"}},{"zimo":{"l":3,"p":"m8"}},{"dapai":{"l":3,"p":"m8_"}},{"zimo":{"l":0,"p":"z6"}},{"dapai":{"l":0,"p":"z6_"}},{"zimo":{"l":1,"p":"z7"}},{"dapai":{"l":1,"p":"z7_"}},{"zimo":{"l":2,"p":"p8"}},{"dapai":{"l":2,"p":"p8"}},{"zimo":{"l":3,"p":"p1"}},{"dapai":{"l":3,"p":"p5"}},{"zimo":{"l":0,"p":"m8"}},{"dapai":{"l":0,"p":"m8_"}},{"zimo":{"l":1,"p":"z5"}},{"dapai":{"l":1,"p":"z5_"}},{"zimo":{"l":2,"p":"s2"}},{"dapai":{"l":2,"p":"s2_"}},{"zimo":{"l":3,"p":"p2"}},{"dapai":{"l":3,"p":"s4"}},{"hule":{"chongjia":3,"l":1,"shoupai":"s23456z77s4,s111+,s456-","zongfen":8,"fanzhong":[{"name_zh":"混一色","fenshu":6},{"name_zh":"喜相逢","fenshu":1},{"name_zh":"幺九刻","fenshu":1}],"fenpei":[-8,32,-8,-16]}}],
[{"qipai":{"quanfeng":0,"jushu":3,"zuoci":[3,0,1,2],"defen":[7,77,-41,-43],"shoupai":["m35p24679s158z235","m13778p1346s3789","m156899p128s3z157","m449p469s45677z16"]}},{"zimo":{"l":0,"p":"z4"}},{"dapai":{"l":0,"p":"z2"}},{"zimo":{"l":1,"p":"m2"}},{"dapai":{"l":1,"p":"m8"}},{"zimo":{"l":2,"p":"m2"}},{"dapai":{"l":2,"p":"z5"}},{"zimo":{"l":3,"p":"p5"}},{"dapai":{"l":3,"p":"z1"}},{"zimo":{"l":0,"p":"s9"}},{"dapai":{"l":0,"p":"z5"}},{"zimo":{"l":1,"p":"z6"}},{"dapai":{"l":1,"p":"z6_"}},{"zimo":{"l":2,"p":"m5"}},{"dapai":{"l":2,"p":"z7"}},{"zimo":{"l":3,"p":"m1"}},{"dapai":{"l":3,"p":"z6"}},{"zimo":{"l":0,"p":"m8"}},{"dapai":{"l":0,"p":"z3"}},{"zimo":{"l":1,"p":"p8"}},{"dapai":{"l":1,"p":"p8_"}},{"zimo":{"l":2,"p":"m7"}},{"dapai":{"l":2,"p":"z1"}},{"zimo":{"l":3,"p":"m7"}},{"dapai":{"l":3,"p":"m1"}},{"zimo":{"l":0,"p":"s5"}},{"dapai":{"l":0,"p":"z4"}},{"zimo":{"l":1,"p":"z5"}},{"dapai":{"l":1,"p":"z5_"}},{"zimo":{"l":2,"p":"p5"}},{"dapai":{"l":2,"p":"p8"}},{"zimo":{"l":3,"p":"s6"}},{"dapai":{"l":3,"p":"p9"}},{"zimo":{"l":0,"p":"s7"}},{"dapai":{"l":0,"p":"s1"}},{"zimo":{"l":1,"p":"m8"}},{"dapai":{"l":1,"p":"m8_"}},{"zimo":{"l":2,"p":"p9"}},{"dapai":{"l":2,"p":"p9_"}},{"zimo":{"l":3,"p":"m6"}},{"dapai":{"l":3,"p":"m9"}},{"fulou":{"l":2,"m":"m999+"}},{"dapai":{"l":2,"p":"p5"}},{"zimo":{"l":3,"p":"s2"}},{"dapai":{"l":3,"p":"s2_"}},{"zimo":{"l":0,"p":"p7"}},{"dapai":{"l":0,"p":"p9"}},{"zimo":{"l":1,"p":"s2"}},{"dapai":{"l":1,"p":"p1"}},{"zimo":{"l":2,"p":"s3"}},{"dapai":{"l":2,"p":"p1"}},{"zimo":{"l":3,"p":"z3"}},{"dapai":{"l":3,"p":"z3_"}},{"zimo":{"l":0,"p":"m6"}},{"dapai":{"l":0,"p":"p7"}},{"zimo":{"l":1,"p":"p5"}},{"dapai":{"l":1,"p":"p3"}},{"zimo":{"l":2,"p":"s1"}},{"dapai":{"l":2,"p":"p2"}},{"zimo":{"l":3,"p":"z2"}},{"dapai":{"l":3,"p":"z2_"}},{"zimo":{"l":0,"p":"s1"}},{"dapai":{"l":0,"p":"s1_"}},{"hule":{"chongjia":0,"l":1,"shoupai":"m12377p456s23789s1_","zongfen":13,"fanzhong":[{"name_zh":"花龙","fenshu":8},{"name_zh":"门前清","fenshu":2},{"name_zh":"平和","fenshu":2},{"name_zh":"老少副","fenshu":1}],"fenpei":[-21,37,-8,-8]}}],
[{"qipai":{"quanfeng":1,"jushu":0,"zuoci":[0,1,2,3],"defen":[114,-49,-51,-14],"shoupai":["m3p27s2899z345666","m13468p34567z112","m346p24459s13z156","m467p6689s11z3577"]}},{"zimo":{"l":0,"p":"p1"}},{"dapai":{"l":0,"p":"s2"}},{"zimo":{"l":1,"p":"s2"}},{"dapai":{"l":1,"p":"z2"}},{"zimo":{"l":2,"p":"z7"}},{"dapai":{"l":2,"p":"z7_"}},{"zimo":{"l":3,"p":"s7"}},{"dapai":{"l":3,"p":"z5"}},{"zimo":{"l":0,"p":"m3"}},{"dapai":{"l":0,"p":"z5"}},{"zimo":{"l":1,"p":"p3"}},{"dapai":{"l":1,"p":"z1"}},{"zimo":{"l":2,"p":"s3"}},{"dapai":{"l":2,"p":"z5"}},{"zimo":{"l":3,"p":"s4"}},{"dapai":{"l":3,"p":"m4"}},{"zimo":{"l":0,"p":"p9"}},{"dapai":{"l":0,"p":"p1"}},{"zimo":{"l":1,"p":"m8"}},{"dapai":{"l":1,"p":"z1"}},{"zimo":{"l":2,"p":"s6"}},{"dapai":{"l":2,"p":"z6"}},{"zimo":{"l":3,"p":"s6"}},{"dapai":{"l":3,"p":"s4"}},{"zimo":{"l":0,"p":"p5"}},{"dapai":{"l":0,"p":"p2"}},{"zimo":{"l":1,"p":"s6"}},{"dapai":{"l":1,"p":"m1"}},{"zimo":{"l":2,"p":"p8"}},{"dapai":{"l":2,"p":"z1"}},{"zimo":{"l":3,"p":"m7"}},{"dapai":{"l":3,"p":"z3"}},{"zimo":{"l":0,"p":"s5"}},{"dapai":{"l":0,"p":"s5_"}},{"zimo":{"l":1,"p":"p2"}},{"dapai":{"l":1,"p":"m6"}},{"zimo":{"l":2,"p":"s4"}},{"dapai":{"l":2,"p":"p9"}},{"zimo":{"l":3,"p":"s2"}},{"dapai":{"l":3,"p":"s2_"}},{"zimo":{"l":0,"p":"z5"}},{"dapai":{"l":0,"p":"z5_"}},{"zimo":{"l":1,"p":"m5"}},{"dapai":{"l":1,"p":"s2"}},{"fulou":{"l":2,"m":"s12-3"}},{"dapai":{"l":2,"p":"p8"}},{"zimo":{"l":3,"p":"s9"}},{"dapai":{"l":3,"p":"s9_"}},{"fulou":{"l":0,"m":"s999-"}},{"dapai":{"l":0,"p":"s8"}},{"zimo":{"l":1,"p":"z4"}},{"dapai":{"l":1,"p":"z4_"}},{"zimo":{"l":2,"p":"m8"}},{"dapai":{"l":2,"p":"m8_"}},{"fulou":{"l":3,"m":"m678-"}},{"dapai":{"l":3,"p":"m7"}},{"zimo":{"l":0,"p":"p1"}},{"dapai":{"l":0,"p":"p1_"}},{"fulou":{"l":1,"m":"p1-23"}},{"dapai":{"l":1,"p":"s6"}},{"zimo":{"l":2,"p":"m9"}},{"dapai":{"l":2,"p":"m9_"}},{"zimo":{"l":3,"p":"z3"}},{"dapai":{"l":3,"p":"z3_"}},{"zimo":{"l":0,"p":"p8"}},{"dapai":{"l":0,"p":"p5"}},{"hule":{"chongjia":0,"l":1,"shoupai":"m34588p34567p5,p1-23","zongfen":20,"fanzhong":[{"name_zh":"一色三步高","fenshu":16},{"name_zh":"平和","fenshu":2},{"name_zh":"缺一门","fenshu":1},{"name_zh":"喜相逢","fenshu":1}],"fenpei":[-28,44,-8,-8]}}],
[{"qipai":{"quanfeng":1,"jushu":1,"zuoci":[1,2,3,0],"defen":[-5,-59,-22,86],"shoupai":["m3446p13s123347z1","m7899p39s156789z5","m277p4556679s1z37","m455p14s339z13357"]}},{"zimo":{"l":0,"p":"m8"}},{"dapai":{"l":0,"p":"z1"}},{"zimo":{"l":1,"p":"m9"}},{"dapai":{"l":1,"p":"z5"}},{"zimo":{"l":2,"p":"p2"}},{"dapai":{"l":2,"p":"s1"}},{"zimo":{"l":3,"p":"p8"}},{"dapai":{"l":3,"p":"z1"}},{"zimo":{"l":0,"p":"z2"}},{"dapai":{"l":0,"p":"z2_"}},{"zimo":{"l":1,"p":"m1"}},{"dapai":{"l":1,"p":"m1_"}},{"zimo":{"l":2,"p":"m5"}},{"dapai":{"l":2,"p":"z7"}},{"zimo":{"l":3,"p":"z5"}},{"dapai":{"l":3,"p":"z7"}},{"zimo":{"l":0,"p":"s8"}},{"dapai":{"l":0,"p":"m8"}},{"zimo":{"l":1,"p":"p3"}},{"dapai":{"l":1,"p":"p3_"}},{"fulou":{"l":2,"m":"p23-4"}},{"dapai":{"l":2,"p":"m2"}},{"zimo":{"l":3,"p":"m1"}},{"dapai":{"l":3,"p":"m1_"}},{"zimo":{"l":0,"p":"p5"}},{"dapai":{"l":0,"p":"m4"}},{"zimo":{"l":1,"p":"s7"}},{"dapai":{"l":1,"p":"p3"}},{"zimo":{"l":2,"p":"z1"}},{"dapai":{"l":2,"p":"z1_"}},{"zimo":{"l":3,"p":"p3"}},{"dapai":{"l":3,"p":"p1"}},{"zimo":{"l":0,"p":"z6"}},{"dapai":{"l":0,"p":"z6_"}},{"zimo":{"l":1,"p":"s5"}},{"dapai":{"l":1,"p":"s1"}},{"zimo":{"l":2,"p":"m6"}},{"dapai":{"l":2,"p":"z3"}},{"fulou":{"l":3,"m":"z333-"}},{"dapai":{"l":3,"p":"p8"}},{"zimo":{"l":0,"p":"s8"}},{"dapai":{"l":0,"p":"s7"}},{"zimo":{"l":1,"p":"z7"}},{"dapai":{"l":1,"p":"z7_"}},{"zimo":{"l":2,"p":"p5"}},{"dapai":{"l":2,"p":"m7"}},{"zimo":{"l":3,"p":"p8"}},{"dapai":{"l":3,"p":"p8_"}},{"zimo":{"l":0,"p":"p7"}},{"dapai":{"l":0,"p":"m6"}},{"zimo":{"l":1,"p":"m5"}},{"dapai":{"l":1,"p":"m5_"}},{"fulou":{"l":3,"m":"m555="}},{"dapai":{"l":3,"p":"m4"}},{"zimo":{"l":0,"p":"p6"}},{"dapai":{"l":0,"p":"m4"}},{"zimo":{"l":1,"p":"p1"}},{"dapai":{"l":1,"p":"p1_"}},{"zimo":{"l":2,"p":"p4"}},{"dapai":{"l":2,"p":"p9"}},{"zimo":{"l":3,"p":"m2"}},{"dapai":{"l":3,"p":"m2_"}},{"zimo":{"l":0,"p":"z2"}},{"dapai":{"l":0,"p":"z2_"}},{"zimo":{"l":1,"p":"p1"}},{"dapai":{"l":1,"p":"p1_"}},{"zimo":{"l":2,"p":"m2"}},{"dapai":{"l":2,"p":"m2_"}},{"zimo":{"l":3,"p":"s9"}},{"dapai":{"l":3,"p":"s3"}},{"zimo":{"l":0,"p":"p2"}},{"dapai":{"l":0,"p":"m3"}},{"zimo":{"l":1,"p":"m1"}},{"dapai":{"l":1,"p":"m1_"}},{"zimo":{"l":2,"p":"m6"}},{"dapai":{"l":2,"p":"m6"}},{"zimo":{"l":3,"p":"s9"}},{"dapai":{"l":3,"p":"s3"}},{"zimo":{"l":0,"p":"p8"}},{"dapai":{"l":0,"p":"p8_"}},{"hule":{"chongjia":0,"l":2,"shoupai":"m567p4555667p8_,p23-4","zongfen":21,"fanzhong":[{"name_zh":"一色三步高","fenshu":16},{"name_zh":"断幺","fenshu":2},{"name_zh":"平和","fenshu":2},{"name_zh":"缺一门","fenshu":1}],"fenpei":[-29,-8,45,-8]}}],
[{"qipai":{"quanfeng":1,"jushu":2,"zuoci":[2,3,0,1],"defen":[-67,23,78,-34],"shoupai":["m3478p2337s25567","m4455p14569s338z3","m6p2469s2257z4667","m113p1467s1359z17"]}},{"zimo":{"l":0,"p":"m2"}},{"dapai":{"l":0,"p":"s2"}},{"zimo":{"l":1,"p":"s8"}},{"dapai":{"l":1,"p":"z3"}},{"zimo":{"l":2,"p":"z1"}},{"dapai":{"l":2,"p":"p9"}},{"zimo":{"l":3,"p":"p9"}},{"dapai":{"l":3,"p":"z1"}},{"zimo":{"l":0,"p":"m2"}},{"dapai":{"l":0,"p":"m2_"}},{"zimo":{"l":1,"p":"s1"}},{"dapai":{"l":1,"p":"p9"}},{"zimo":{"l":2,"p":"m7"}},{"dapai":{"l":2,"p":"z7"}},{"zimo":{"l":3,"p":"m6"}},{"dapai":{"l":3,"p":"z7"}},{"zimo":{"l":0,"p":"m6"}},{"dapai":{"l":0,"p":"p2"}},{"zimo":{"l":1,"p":"m1"}},{"dapai":{"l":1,"p":"m1_"}},{"zimo":{"l":2,"p":"p6"}},{"dapai":{"l":2,"p":"p2"}},{"zimo":{"l":3,"p":"z1"}},{"dapai":{"l":3,"p":"z1_"}},{"zimo":{"l":0,"p":"m3"}},{"dapai":{"l":0,"p":"m3_"}},{"zimo":{"l":1,"p":"p7"}},{"dapai":{"l":1,"p":"p1"}},{"zimo":{"l":2,"p":"s1"}},{"dapai":{"l":2,"p":"s1_"}},{"zimo":{"l":3,"p":"p8"}},{"dapai":{"l":3,"p":"s9"}},{"zimo":{"l":0,"p":"m7"}},{"dapai":{"l":0,"p":"m7_"}},{"zimo":{"l":1,"p":"z3"}},{"dapai":{"l":1,"p":"z3_"}},{"zimo":{"l":2,"p":"s3"}},{"dapai":{"l":2,"p":"p6"}},{"zimo":{"l":3,"p":"p1"}},{"dapai":{"l":3,"p":"m6"}},{"fulou":{"l":0,"m":"m6-78"}},{"dapai":{"l":0,"p":"s5"}},{"zimo":{"l":1,"p":"p3"}},{"dapai":{"l":1,"p":"s3"}},{"zimo":{"l":2,"p":"z4"}},{"dapai":{"l":2,"p":"z1"}},{"zimo":{"l":3,"p":"z1"}},{"dapai":{"l":3,"p":"z1_"}},{"zimo":{"l":0,"p":"p8"}},{"dapai":{"l":0,"p":"m6"}},{"fulou":{"l":1,"m":"m456-"}},{"dapai":{"l":1,"p":"p7"}},{"zimo":{"l":2,"p":"m9"}},{"dapai":{"l":2,"p":"m9_"}},{"zimo":{"l":3,"p":"z5"}},{"dapai":{"l":3,"p":"z5_"}},{"zimo":{"l":0,"p":"s4"}},{"dapai":{"l":0,"p":"s4_"}},{"zimo":{"l":1,"p":"z7"}},{"dapai":{"l":1,"p":"z7_"}},{"zimo":{"l":2,"p":"m8"}},{"dapai":{"l":2,"p":"s3"}},{"zimo":{"l":3,"p":"p5"}},{"dapai":{"l":3,"p":"s5"}},{"zimo":{"l":0,"p":"m2"}},{"dapai":{"l":0,"p":"m2_"}},{"zimo":{"l":1,"p":"m4"}},{"dapai":{"l":1,"p":"m4"}},{"zimo":{"l":2,"p":"s9"}},{"dapai":{"l":2,"p":"s2"}},{"zimo":{"l":3,"p":"z3"}},{"dapai":{"l":3,"p":"z3_"}},{"zimo":{"l":0,"p":"s4"}},{"dapai":{"l":0,"p":"s4_"}},{"zimo":{"l":1,"p":"p5"}},{"dapai":{"l":1,"p":"s1"}},{"zimo":{"l":2,"p":"z6"}},{"dapai":{"l":2,"p":"s2"}},{"zimo":{"l":3,"p":"s7"}},{"dapai":{"l":3,"p":"s7_"}},{"zimo":{"l":0,"p":"s4"}},{"dapai":{"l":0,"p":"s4_"}},{"zimo":{"l":1,"p":"p7"}},{"dapai":{"l":1,"p":"s3"}},{"zimo":{"l":2,"p":"m7"}},{"dapai":{"l":2,"p":"m7"}},{"zimo":{"l":3,"p":"m2"}},{"dapai":{"l":3,"p":"m1"}},{"zimo":{"l":0,"p":"p4"}},{"dapai":{"l":0,"p":"p4_"}},{"fulou":{"l":1,"m":"p34-5"}},{"dapai":{"l":1,"p":"s8"}},{"fulou":{"l":2,"m":"s78-9"}},{"dapai":{"l":2,"p":"s5"}},{"zimo":{"l":3,"p":"m3"}},{"dapai":{"l":3,"p":"m3_"}},{"zimo":{"l":0,"p":"z2"}},{"dapai":{"l":0,"p":"z2_"}},{"zimo":{"l":1,"p":"z4"}},{"dapai":{"l":1,"p":"s8"}},{"zimo":{"l":2,"p":"z2"}},{"dapai":{"l":2,"p":"z2_"}},{"zimo":{"l":3,"p":"s6"}},{"dapai":{"l":3,"p":"s6_"}},{"zimo":{"l":0,"p":"s4"}},{"dapai":{"l":0,"p":"s4_"}},{"zimo":{"l":1,"p":"s8"}},{"dapai":{"l":1,"p":"s8_"}},{"zimo":{"l":2,"p":"p3"}},{"dapai":{"l":2,"p":"p6"}},{"zimo":{"l":3,"p":"z7"}},{"dapai":{"l":3,"p":"z7_"}},{"zimo":{"l":0,"p":"m8"}},{"dapai":{"l":0,"p":"m8_"}},{"zimo":{"l":1,"p":"m9"}},{"dapai":{"l":1,"p":"m9_"}},{"zimo":{"l":2,"p":"s1"}},{"dapai":{"l":2,"p":"s1_"}},{"zimo":{"l":3,"p":"z2"}},{"dapai":{"l":3,"p":"z2_"}},{"zimo":{"l":0,"p":"z4"}},{"dapai":{"l":0,"p":"z4_"}},{"zimo":{"l":1,"p":"m5"}},{"dapai":{"l":1,"p":"z4"}},{"zimo":{"l":2,"p":"z5"}},{"dapai":{"l":2,"p":"z5_"}},{"zimo":{"l":3,"p":"z5"}},{"dapai":{"l":3,"p":"z5_"}},{"zimo":{"l":0,"p":"p8"}},{"dapai":{"l":0,"p":"p8_"}},{"fulou":{"l":1,"m":"p678-"}},{"dapai":{"l":1,"p":"m4"}},{"zimo":{"l":2,"p":"z5"}},{"dapai":{"l":2,"p":"z5_"}},{"zimo":{"l":3,"p":"s9"}},{"dapai":{"l":3,"p":"s9_"}},{"zimo":{"l":0,"p":"p2"}},{"dapai":{"l":0,"p":"p2_"}},{"hule":{"chongjia":0,"l":2,"shoupai":"m678p34z44666p2_,s78-9","zongfen":8,"fanzhong":[{"name_zh":"五门齐","fenshu":6},{"name_zh":"箭刻","fenshu":2}],"fenpei":[-16,-8,32,-8]}}],
[{"qipai":{"quanfeng":1,"jushu":3,"zuoci":[3,0,1,2],"defen":[15,110,-42,-83],"shoupai":["m89p12299s2569z35","m124p68s2345z1246","m4557p28s1167z247","m17p466s1234467z6"]}},{"zimo":{"l":0,"p":"m4"}},{"dapai":{"l":0,"p":"z5"}},{"zimo":{"l":1,"p":"m6"}},{"dapai":{"l":1,"p":"z4"}},{"zimo":{"l":2,"p":"z3"}},{"dapai":{"l":2,"p":"z4"}},{"zimo":{"l":3,"p":"s8"}},{"dapai":{"l":3,"p":"z6"}},{"zimo":{"l":0,"p":"p7"}},{"dapai":{"l":0,"p":"z3"}},{"zimo":{"l":1,"p":"p1"}},{"dapai":{"l":1,"p":"z1"}},{"zimo":{"l":2,"p":"p3"}},{"dapai":{"l":2,"p":"z3"}},{"zimo":{"l":3,"p":"s5"}},{"dapai":{"l":3,"p":"m1"}},{"zimo":{"l":0,"p":"m7"}},{"dapai":{"l":0,"p":"s2"}},{"zimo":{"l":1,"p":"s7"}},{"dapai":{"l":1,"p":"z6"}},{"zimo":{"l":2,"p":"m9"}},{"dapai":{"l":2,"p":"z2"}},{"zimo":{"l":3,"p":"s3"}},{"dapai":{"l":3,"p":"m7"}},{"zimo":{"l":0,"p":"m3"}},{"dapai":{"l":0,"p":"s9"}},{"zimo":{"l":1,"p":"s9"}},{"dapai":{"l":1,"p":"z2"}},{"zimo":{"l":2,"p":"z7"}},{"dapai":{"l":2,"p":"p8"}},{"zimo":{"l":3,"p":"p3"}},{"dapai":{"l":3,"p":"s1"}},{"zimo":{"l":0,"p":"m2"}},{"dapai":{"l":0,"p":"p2"}},{"hule":{"chongjia":0,"l":3,"shoupai":"p3466s233445678p2","zongfen":9,"fanzhong":[{"name_zh":"门前清","fenshu":2},{"name_zh":"断幺","fenshu":2},{"name_zh":"平和","fenshu":2},{"name_zh":"缺一门","fenshu":1},{"name_zh":"连六","fenshu":1},{"name_zh":"喜相逢","fenshu":1}],"fenpei":[-17,-8,-8,33]}}],
[{"qipai":{"quanfeng":2,"jushu":0,"zuoci":[1,0,3,2],"defen":[-50,102,-2,-50],"shoupai":["m55p356678s66z477","m68p358s1457z2556","m234778p7s23788z1","m2366p12299s456z1"]}},{"zimo":{"l":0,"p":"m2"}},{"dapai":{"l":0,"p":"m2"}},{"zimo":{"l":1,"p":"m1"}},{"dapai":{"l":1,"p":"s1"}},{"zimo":{"l":2,"p":"p4"}},{"dapai":{"l":2,"p":"z1"}},{"zimo":{"l":3,"p":"m1"}},{"dapai":{"l":3,"p":"z1"}},{"zimo":{"l":0,"p":"p6"}},{"dapai":{"l":0,"p":"z4"}},{"zimo":{"l":1,"p":"p6"}},{"dapai":{"l":1,"p":"p8"}},{"zimo":{"l":2,"p":"z3"}},{"dapai":{"l":2,"p":"z3_"}},{"zimo":{"l":3,"p":"z1"}},{"dapai":{"l":3,"p":"z1_"}},{"zimo":{"l":0,"p":"z4"}},{"dapai":{"l":0,"p":"z4_"}},{"zimo":{"l":1,"p":"p9"}},{"dapai":{"l":1,"p":"p9_"}},{"zimo":{"l":2,"p":"m7"}},{"dapai":{"l":2,"p":"p4"}},{"zimo":{"l":3,"p":"s4"}},{"dapai":{"l":3,"p":"s4_"}},{"zimo":{"l":0,"p":"m9"}},{"dapai":{"l":0,"p":"m9_"}},{"zimo":{"l":1,"p":"p5"}},{"dapai":{"l":1,"p":"z6"}},{"zimo":{"l":2,"p":"m3"}},{"dapai":{"l":2,"p":"m3_"}},{"zimo":{"l":3,"p":"m4"}},{"dapai":{"l":3,"p":"p2"}},{"zimo":{"l":0,"p":"z6"}},{"dapai":{"l":0,"p":"z6_"}},{"zimo":{"l":1,"p":"z3"}},{"dapai":{"l":1,"p":"m1"}},{"zimo":{"l":2,"p":"p4"}},{"dapai":{"l":2,"p":"p4_"}},{"zimo":{"l":3,"p":"z6"}},{"dapai":{"l":3,"p":"z6_"}},{"zimo":{"l":0,"p":"s7"}},{"dapai":{"l":0,"p":"p3"}},{"zimo":{"l":1,"p":"m1"}},{"dapai":{"l":1,"p":"p3"}},{"zimo":{"l":2,"p":"z2"}},{"dapai":{"l":2,"p":"z2_"}},{"zimo":{"l":3,"p":"m5"}},{"dapai":{"l":3,"p":"m6"}},{"zimo":{"l":0,"p":"z3"}},{"dapai":{"l":0,"p":"z3_"}},{"zimo":{"l":1,"p":"s1"}},{"dapai":{"l":1,"p":"m1"}},{"zimo":{"l":2,"p":"p2"}},{"dapai":{"l":2,"p":"p2_"}},{"zimo":{"l":3,"p":"s8"}},{"dapai":{"l":3,"p":"s8_"}},{"zimo":{"l":0,"p":"p3"}},{"dapai":{"l":0,"p":"p3_"}},{"hule":{"chongjia":0,"l":3,"shoupai":"m123456p1299s456p3_","zongfen":8,"fanzhong":[{"name_zh":"门前清","fenshu":2},{"name_zh":"平和","fenshu":2},{"name_zh":"连六","fenshu":1},{"name_zh":"喜相逢","fenshu":1},{"name_zh":"喜相逢","fenshu":1},{"name_zh":"边张","fenshu":1}],"fenpei":[-16,-8,-8,32]}}],
[{"qipai":{"quanfeng":2,"jushu":1,"zuoci":[0,3,2,1],"defen":[94,-10,-18,-66],"shoupai":["m789p166s1378z115","m3679p5789s277z35","m13479p34s234z247","m18p1238s1599z467"]}},{"zimo":{"l":0,"p":"p6"}},{"dapai":{"l":0,"p":"p1"}},{"zimo":{"l":1,"p":"p7"}},{"dapai":{"l":1,"p":"z5"}},{"zimo":{"l":2,"p":"p8"}},{"dapai":{"l":2,"p":"z2"}},{"zimo":{"l":3,"p":"s5"}},{"dapai":{"l":3,"p":"z4"}},{"zimo":{"l":0,"p":"z6"}},{"dapai":{"l":0,"p":"s1"}},{"zimo":{"l":1,"p":"p4"}},{"dapai":{"l":1,"p":"z3"}},{"zimo":{"l":2,"p":"m9"}},{"dapai":{"l":2,"p":"z7"}},{"zimo":{"l":3,"p":"p3"}},{"dapai":{"l":3,"p":"z6"}},{"zimo":{"l":0,"p":"s8"}},{"dapai":{"l":0,"p":"s3"}},{"zimo":{"l":1,"p":"s6"}},{"dapai":{"l":1,"p":"m3"}},{"zimo":{"l":2,"p":"m6"}},{"dapai":{"l":2,"p":"z4"}},{"zimo":{"l":3,"p":"s3"}},{"dapai":{"l":3,"p":"z7"}},{"zimo":{"l":0,"p":"p2"}},{"dapai":{"l":0,"p":"p2_"}},{"zimo":{"l":1,"p":"m3"}},{"dapai":{"l":1,"p":"m3_"}},{"zimo":{"l":2,"p":"p7"}},{"dapai":{"l":2,"p":"p8"}},{"zimo":{"l":3,"p":"m5"}},{"dapai":{"l":3,"p":"m5_"}},{"zimo":{"l":0,"p":"z2"}},{"dapai":{"l":0,"p":"z2_"}},{"zimo":{"l":1,"p":"s1"}},{"dapai":{"l":1,"p":"p7"}},{"zimo":{"l":2,"p":"s8"}},{"dapai":{"l":2,"p":"s8_"}},{"fulou":{"l":0,"m":"s888="}},{"dapai":{"l":0,"p":"s7"}},{"zimo":{"l":1,"p":"p5"}},{"dapai":{"l":1,"p":"s7"}},{"zimo":{"l":2,"p":"p8"}},{"dapai":{"l":2,"p":"p8_"}},{"zimo":{"l":3,"p":"s8"}},{"dapai":{"l":3,"p":"m8"}},{"zimo":{"l":0,"p":"m6"}},{"dapai":{"l":0,"p":"m9"}},{"zimo":{"l":1,"p":"z4"}},{"dapai":{"l":1,"p":"z4_"}},{"zimo":{"l":2,"p":"p9"}},{"dapai":{"l":2,"p":"p9_"}},{"zimo":{"l":3,"p":"s4"}},{"dapai":{"l":3,"p":"p8"}},{"zimo":{"l":0,"p":"p2"}},{"dapai":{"l":0,"p":"p2_"}},{"zimo":{"l":1,"p":"p9"}},{"dapai":{"l":1,"p":"p9"}},{"zimo":{"l":2,"p":"m3"}},{"dapai":{"l":2,"p":"p7"}},{"zimo":{"l":3,"p":"z2"}},{"dapai":{"l":3,"p":"z2_"}},{"zimo":{"l":0,"p":"z5"}},{"dapai":{"l":0,"p":"z6"}},{"zimo":{"l":1,"p":"m4"}},{"dapai":{"l":1,"p":"p4"}},{"zimo":{"l":2,"p":"z3"}},{"dapai":{"l":2,"p":"z3_"}},{"zimo":{"l":3,"p":"z6"}},{"dapai":{"l":3,"p":"z6_"}},{"zimo":{"l":0,"p":"m7"}},{"dapai":{"l":0,"p":"m7"}},{"zimo":{"l":1,"p":"z3"}},{"dapai":{"l":1,"p":"z3_"}},{"zimo":{"l":2,"p":"m6"}},{"dapai":{"l":2,"p":"m3"}},{"zimo":{"l":3,"p":"z1"}},{"dapai":{"l":3,"p":"z1_"}},{"hule":{"chongjia":3,"l":0,"shoupai":"m678p666z1155z1_,s888=","zongfen":8,"fanzhong":[{"name_zh":"五门齐","fenshu":6},{"name_zh":"门风刻","fenshu":2}],"fenpei":[32,-8,-8,-16]}}],
[{"qipai":{"quanfeng":2,"jushu":2,"zuoci":[3,2,1,0],"defen":[-18,-26,-82,126],"shoupai":["m57p14s33456z1345","m23p46689s267z235","m4p335s134799z557","m2279p2559s1489z7"]}},{"zimo":{"l":0,"p":"m7"}},{"dapai":{"l":0,"p":"z4"}},{"zimo":{"l":1,"p":"z1"}},{"dapai":{"l":1,"p":"z1_"}},{"zimo":{"l":2,"p":"z6"}},{"dapai":{"l":2,"p":"m4"}},{"zimo":{"l":3,"p":"z6"}},{"dapai":{"l":3,"p":"z7"}},{"zimo":{"l":0,"p":"m8"}},{"dapai":{"l":0,"p":"z1"}},{"zimo":{"l":1,"p":"z4"}},{"dapai":{"l":1,"p":"z4_"}},{"zimo":{"l":2,"p":"p8"}},{"dapai":{"l":2,"p":"p8_"}},{"zimo":{"l":3,"p":"m4"}},{"dapai":{"l":3,"p":"z6"}},{"zimo":{"l":0,"p":"z6"}},{"dapai":{"l":0,"p":"z6_"}},{"zimo":{"l":1,"p":"s6"}},{"dapai":{"l":1,"p":"z3"}},{"zimo":{"l":2,"p":"z2"}},{"dapai":{"l":2,"p":"z6"}},{"zimo":{"l":3,"p":"p1"}},{"dapai":{"l":3,"p":"s1"}},{"zimo":{"l":0,"p":"m6"}},{"dapai":{"l":0,"p":"z3"}},{"zimo":{"l":1,"p":"s2"}},{"dapai":{"l":1,"p":"z5"}},{"fulou":{"l":2,"m":"z555-"}},{"dapai":{"l":2,"p":"p5"}},{"zimo":{"l":3,"p":"m8"}},{"dapai":{"l":3,"p":"p5"}},{"zimo":{"l":0,"p":"s2"}},{"dapai":{"l":0,"p":"z5"}},{"zimo":{"l":1,"p":"z4"}},{"dapai":{"l":1,"p":"z4_"}},{"zimo":{"l":2,"p":"m3"}},{"dapai":{"l":2,"p":"m3_"}},{"zimo":{"l":3,"p":"p7"}},{"dapai":{"l":3,"p":"m4"}},{"zimo":{"l":0,"p":"p2"}},{"dapai":{"l":0,"p":"s2"}},{"fulou":{"l":1,"m":"s222-"}},{"dapai":{"l":1,"p":"z2"}},{"zimo":{"l":2,"p":"z2"}},{"dapai":{"l":2,"p":"z7"}},{"zimo":{"l":3,"p":"p2"}},{"dapai":{"l":3,"p":"s4"}},{"zimo":{"l":0,"p":"z1"}},{"dapai":{"l":0,"p":"z1_"}},{"zimo":{"l":1,"p":"m1"}},{"dapai":{"l":1,"p":"s7"}},{"zimo":{"l":2,"p":"p1"}},{"dapai":{"l":2,"p":"s4"}},{"zimo":{"l":3,"p":"p5"}},{"dapai":{"l":3,"p":"p5"}},{"zimo":{"l":0,"p":"s8"}},{"dapai":{"l":0,"p":"s8_"}},{"zimo":{"l":1,"p":"z4"}},{"dapai":{"l":1,"p":"z4_"}},{"zimo":{"l":2,"p":"z7"}},{"dapai":{"l":2,"p":"z7_"}},{"zimo":{"l":3,"p":"s9"}},{"dapai":{"l":3,"p":"s9_"}},{"fulou":{"l":2,"m":"s999+"}},{"dapai":{"l":2,"p":"s7"}},{"fulou":{"l":3,"m":"s7-89"}},{"dapai":{"l":3,"p":"p5"}},{"zimo":{"l":0,"p":"m6"}},{"dapai":{"l":0,"p":"p1"}},{"zimo":{"l":1,"p":"p3"}},{"dapai":{"l":1,"p":"p3_"}},{"fulou":{"l":2,"m":"p333-"}},{"dapai":{"l":2,"p":"p1"}},{"zimo":{"l":3,"p":"p6"}},{"dapai":{"l":3,"p":"p6_"}},{"fulou":{"l":1,"m":"p666="}},{"dapai":{"l":1,"p":"p4"}},{"zimo":{"l":2,"p":"p9"}},{"dapai":{"l":2,"p":"p9_"}},{"zimo":{"l":3,"p":"s8"}},{"dapai":{"l":3,"p":"s8_"}},{"zimo":{"l":0,"p":"z3"}},{"dapai":{"l":0,"p":"z3_"}},{"zimo":{"l":1,"p":"p4"}},{"dapai":{"l":1,"p":"p4_"}},{"zimo":{"l":2,"p":"p1"}},{"dapai":{"l":2,"p":"p1_"}},{"zimo":{"l":3,"p":"m6"}},{"dapai":{"l":3,"p":"m6_"}},{"zimo":{"l":0,"p":"z6"}},{"dapai":{"l":0,"p":"z6_"}},{"zimo":{"l":1,"p":"m5"}},{"dapai":{"l":1,"p":"m5_"}},{"zimo":{"l":2,"p":"p7"}},{"dapai":{"l":2,"p":"p7_"}},{"zimo":{"l":3,"p":"p3"}},{"dapai":{"l":3,"p":"p2"}},{"zimo":{"l":0,"p":"m8"}},{"dapai":{"l":0,"p":"m5"}},{"zimo":{"l":1,"p":"s1"}},{"dapai":{"l":1,"p":"s1_"}},{"zimo":{"l":2,"p":"p8"}},{"dapai":{"l":2,"p":"p8_"}},{"hule":{"chongjia":2,"l":3,"shoupai":"m22789p12379p8_,s7-89","zongfen":12,"fanzhong":[{"name_zh":"三色三同顺","fenshu":8},{"name_zh":"平和","fenshu":2},{"name_zh":"老少副","fenshu":1},{"name_zh":"坎张","fenshu":1}],"fenpei":[-8,-8,-20,36]}}],
[{"qipai":{"quanfeng":2,"jushu":3,"zuoci":[2,1,0,3],"defen":[-34,-102,162,-26],"shoupai":["m7p148899s4479z46","m36689p26z113567","m359p25s246678z22","m24569p3446s2z667"]}},{"zimo":{"l":0,"p":"p6"}},{"dapai":{"l":0,"p":"z4"}},{"zimo":{"l":1,"p":"p9"}},{"dapai":{"l":1,"p":"p6"}},{"zimo":{"l":2,"p":"s5"}},{"dapai":{"l":2,"p":"m9"}},{"zimo":{"l":3,"p":"p9"}},{"dapai":{"l":3,"p":"z7"}},{"zimo":{"l":0,"p":"m3"}},{"dapai":{"l":0,"p":"z6"}},{"zimo":{"l":1,"p":"m7"}},{"dapai":{"l":1,"p":"p2"}},{"zimo":{"l":2,"p":"z1"}},{"dapai":{"l":2,"p":"p2"}},{"zimo":{"l":3,"p":"s3"}},{"dapai":{"l":3,"p":"m9"}},{"zimo":{"l":0,"p":"m4"}},{"dapai":{"l":0,"p":"m7"}},{"zimo":{"l":1,"p":"m8"}},{"dapai":{"l":1,"p":"p9"}},{"zimo":{"l":2,"p":"p5"}},{"dapai":{"l":2,"p":"z1"}},{"zimo":{"l":3,"p":"p7"}},{"dapai":{"l":3,"p":"m2"}},{"zimo":{"l":0,"p":"s7"}},{"dapai":{"l":0,"p":"p1"}},{"zimo":{"l":1,"p":"p7"}},{"dapai":{"l":1,"p":"p7_"}},{"zimo":{"l":2,"p":"s8"}},{"dapai":{"l":2,"p":"z2"}},{"zimo":{"l":3,"p":"z3"}},{"dapai":{"l":3,"p":"p6"}},{"zimo":{"l":0,"p":"m8"}},{"dapai":{"l":0,"p":"m8_"}},{"zimo":{"l":1,"p":"p2"}},{"dapai":{"l":1,"p":"p2_"}},{"zimo":{"l":2,"p":"z1"}},{"dapai":{"l":2,"p":"z1_"}},{"fulou":{"l":1,"m":"z111+"}},{"dapai":{"l":1,"p":"z6"}},{"fulou":{"l":3,"m":"z666="}},{"dapai":{"l":3,"p":"p3"}},{"zimo":{"l":0,"p":"z5"}},{"dapai":{"l":0,"p":"z5_"}},{"zimo":{"l":1,"p":"z3"}},{"dapai":{"l":1,"p":"z5"}},{"zimo":{"l":2,"p":"m6"}},{"dapai":{"l":2,"p":"z2"}},{"zimo":{"l":3,"p":"s2"}},{"dapai":{"l":3,"p":"s2_"}},{"zimo":{"l":0,"p":"p7"}},{"dapai":{"l":0,"p":"p6"}},{"zimo":{"l":1,"p":"s1"}},{"dapai":{"l":1,"p":"s1_"}},{"zimo":{"l":2,"p":"m1"}},{"dapai":{"l":2,"p":"m1_"}},{"zimo":{"l":3,"p":"s6"}},{"dapai":{"l":3,"p":"s6_"}},{"zimo":{"l":0,"p":"m7"}},{"dapai":{"l":0,"p":"m7_"}},{"fulou":{"l":1,"m":"m7-89"}},{"dapai":{"l":1,"p":"z7"}},{"zimo":{"l":2,"p":"s6"}},{"dapai":{"l":2,"p":"m3"}},{"zimo":{"l":3,"p":"p2"}},{"dapai":{"l":3,"p":"p2_"}},{"zimo":{"l":0,"p":"p8"}},{"dapai":{"l":0,"p":"p4"}},{"zimo":{"l":1,"p":"s8"}},{"dapai":{"l":1,"p":"s8_"}},{"zimo":{"l":2,"p":"s9"}},{"dapai":{"l":2,"p":"s9_"}},{"zimo":{"l":3,"p":"p1"}},{"dapai":{"l":3,"p":"p1_"}},{"zimo":{"l":0,"p":"z7"}},{"dapai":{"l":0,"p":"z7_"}},{"zimo":{"l":1,"p":"m1"}},{"dapai":{"l":1,"p":"m6"}},{"zimo":{"l":2,"p":"p1"}},{"dapai":{"l":2,"p":"p1_"}},{"zimo":{"l":3,"p":"z4"}},{"dapai":{"l":3,"p":"z4_"}},{"zimo":{"l":0,"p":"p3"}},{"dapai":{"l":0,"p":"p3_"}},{"zimo":{"l":1,"p":"s4"}},{"dapai":{"l":1,"p":"s4_"}},{"fulou":{"l":0,"m":"s444+"}},{"dapai":{"l":0,"p":"s9"}},{"zimo":{"l":1,"p":"s8"}},{"dapai":{"l":1,"p":"s8_"}},{"zimo":{"l":2,"p":"z5"}},{"dapai":{"l":2,"p":"z5_"}},{"zimo":{"l":3,"p":"p4"}},{"dapai":{"l":3,"p":"p9"}},{"fulou":{"l":0,"m":"p999-"}},{"dapai":{"l":0,"p":"p7"}},{"zimo":{"l":1,"p":"s2"}},{"dapai":{"l":1,"p":"s2_"}},{"zimo":{"l":2,"p":"m4"}},{"dapai":{"l":2,"p":"s2"}},{"zimo":{"l":3,"p":"z7"}},{"dapai":{"l":3,"p":"p7"}},{"zimo":{"l":0,"p":"m2"}},{"dapai":{"l":0,"p":"m3"}},{"zimo":{"l":1,"p":"m4"}},{"dapai":{"l":1,"p":"m1"}},{"zimo":{"l":2,"p":"m1"}},{"dapai":{"l":2,"p":"m1_"}},{"zimo":{"l":3,"p":"p7"}},{"dapai":{"l":3,"p":"p7_"}},{"zimo":{"l":0,"p":"p6"}},{"dapai":{"l":0,"p":"p6_"}},{"zimo":{"l":1,"p":"m1"}},{"dapai":{"l":1,"p":"m1_"}},{"zimo":{"l":2,"p":"s3"}},{"dapai":{"l":2,"p":"s6"}},{"zimo":{"l":3,"p":"z5"}},{"dapai":{"l":3,"p":"z7"}},{"zimo":{"l":0,"p":"z2"}},{"dapai":{"l":0,"p":"z2_"}},{"zimo":{"l":1,"p":"m2"}},{"hule":{"chongjia":null,"l":1,"shoupai":"m34678z33m2s6,z111+,m7-89","zongfen":8,"fanzhong":[{"name_zh":"混一色","fenshu":6},{"name_zh":"幺九刻","fenshu":1},{"name_zh":"自摸","fenshu":1}],"fenpei":[-16,48,-16,-16]}}],
[{"qipai":{"quanfeng":3,"jushu":0,"zuoci":[1,0,3,2],"defen":[-54,146,-42,-50],"shoupai":["m2348p58s2z124467","m19p23459s25z2336","m589p24678s1569z5","m1247p2s33445677"]}},{"zimo":{"l":0,"p":"p7"}},{"dapai":{"l":0,"p":"z2"}},{"zimo":{"l":1,"p":"m4"}},{"dapai":{"l":1,"p":"m9"}},{"zimo":{"l":2,"p":"p6"}},{"dapai":{"l":2,"p":"z5"}},{"zimo":{"l":3,"p":"p4"}},{"dapai":{"l":3,"p":"m7"}},{"zimo":{"l":0,"p":"s9"}},{"dapai":{"l":0,"p":"z1"}},{"zimo":{"l":1,"p":"m9"}},{"dapai":{"l":1,"p":"m9_"}},{"zimo":{"l":2,"p":"p8"}},{"dapai":{"l":2,"p":"s1"}},{"zimo":{"l":3,"p":"s2"}},{"dapai":{"l":3,"p":"m1"}},{"zimo":{"l":0,"p":"p5"}},{"dapai":{"l":0,"p":"z6"}},{"zimo":{"l":1,"p":"m6"}},{"dapai":{"l":1,"p":"m1"}},{"zimo":{"l":2,"p":"s1"}},{"dapai":{"l":2,"p":"s1_"}},{"zimo":{"l":3,"p":"z7"}},{"dapai":{"l":3,"p":"z7_"}},{"zimo":{"l":0,"p":"p7"}},{"dapai":{"l":0,"p":"z7"}},{"zimo":{"l":1,"p":"m7"}},{"dapai":{"l":1,"p":"z2"}},{"zimo":{"l":2,"p":"p1"}},{"dapai":{"l":2,"p":"s9"}},{"zimo":{"l":3,"p":"m7"}},{"dapai":{"l":3,"p":"m7_"}},{"zimo":{"l":0,"p":"p3"}},{"dapai":{"l":0,"p":"m8"}},{"zimo":{"l":1,"p":"z6"}},{"dapai":{"l":1,"p":"p9"}},{"fulou":{"l":2,"m":"p789-"}},{"dapai":{"l":2,"p":"m5"}},{"zimo":{"l":3,"p":"s5"}},{"dapai":{"l":3,"p":"m2"}},{"zimo":{"l":0,"p":"z6"}},{"dapai":{"l":0,"p":"s9"}},{"zimo":{"l":1,"p":"p9"}},{"dapai":{"l":1,"p":"p9_"}},{"zimo":{"l":2,"p":"s9"}},{"dapai":{"l":2,"p":"s9_"}},{"zimo":{"l":3,"p":"z3"}},{"dapai":{"l":3,"p":"z3_"}},{"fulou":{"l":1,"m":"z333="}},{"dapai":{"l":1,"p":"p2"}},{"zimo":{"l":2,"p":"p2"}},{"dapai":{"l":2,"p":"m9"}},{"zimo":{"l":3,"p":"m5"}},{"dapai":{"l":3,"p":"p2"}},{"fulou":{"l":2,"m":"p222+"}},{"dapai":{"l":2,"p":"m8"}},{"zimo":{"l":3,"p":"m1"}},{"dapai":{"l":3,"p":"m1_"}},{"zimo":{"l":0,"p":"z2"}},{"dapai":{"l":0,"p":"z2_"}},{"zimo":{"l":1,"p":"p1"}},{"dapai":{"l":1,"p":"p1_"}},{"zimo":{"l":2,"p":"s6"}},{"dapai":{"l":2,"p":"s5"}},{"fulou":{"l":3,"m":"s45-6"}},{"dapai":{"l":3,"p":"p4"}},{"fulou":{"l":0,"m":"p34-5"}},{"dapai":{"l":0,"p":"s2"}},{"zimo":{"l":1,"p":"m5"}},{"dapai":{"l":1,"p":"m7"}},{"zimo":{"l":2,"p":"m9"}},{"dapai":{"l":2,"p":"m9_"}},{"zimo":{"l":3,"p":"p5"}},{"dapai":{"l":3,"p":"p5_"}},{"zimo":{"l":0,"p":"p1"}},{"dapai":{"l":0,"p":"z6"}},{"fulou":{"l":1,"m":"z666-"}},{"dapai":{"l":1,"p":"s5"}},{"zimo":{"l":2,"p":"z1"}},{"dapai":{"l":2,"p":"s6"}},{"fulou":{"l":3,"m":"s56-7"}},{"dapai":{"l":3,"p":"m5"}},{"zimo":{"l":0,"p":"p3"}},{"dapai":{"l":0,"p":"p1"}},{"zimo":{"l":1,"p":"m7"}},{"dapai":{"l":1,"p":"m7_"}},{"zimo":{"l":2,"p":"m3"}},{"dapai":{"l":2,"p":"m3_"}},{"zimo":{"l":3,"p":"s8"}},{"dapai":{"l":3,"p":"m4"}},{"zimo":{"l":0,"p":"m8"}},{"dapai":{"l":0,"p":"m8_"}},{"zimo":{"l":1,"p":"z7"}},{"dapai":{"l":1,"p":"z7_"}},{"zimo":{"l":2,"p":"p3"}},{"dapai":{"l":2,"p":"s6"}},{"fulou":{"l":3,"m":"s6-78"}},{"dapai":{"l":3,"p":"s2"}},{"hule":{"chongjia":3,"l":1,"shoupai":"m456p345s2s2,z333=,z666-","zongfen":10,"fanzhong":[{"name_zh":"五门齐","fenshu":6},{"name_zh":"箭刻","fenshu":2},{"name_zh":"幺九刻","fenshu":1},{"name_zh":"单钓将","fenshu":1}],"fenpei":[-8,34,-8,-18]}}],
[{"qipai":{"quanfeng":3,"jushu":1,"zuoci":[0,3,2,1],"defen":[180,-50,-68,-62],"shoupai":["m22355p8s5588z256","m147p3355s339z115","m14479p249s3347z3","m1389p2459s16889"]}},{"zimo":{"l":0,"p":"z2"}},{"dapai":{"l":0,"p":"m3"}},{"zimo":{"l":1,"p":"p4"}},{"dapai":{"l":1,"p":"s9"}},{"zimo":{"l":2,"p":"z2"}},{"dapai":{"l":2,"p":"z2_"}},{"fulou":{"l":0,"m":"z222="}},{"dapai":{"l":0,"p":"p8"}},{"zimo":{"l":1,"p":"m6"}},{"dapai":{"l":1,"p":"m1"}},{"zimo":{"l":2,"p":"p7"}},{"dapai":{"l":2,"p":"z3"}},{"zimo":{"l":3,"p":"m2"}},{"dapai":{"l":3,"p":"p9"}},{"zimo":{"l":0,"p":"z7"}},{"dapai":{"l":0,"p":"z5"}},{"zimo":{"l":1,"p":"z4"}},{"dapai":{"l":1,"p":"z4_"}},{"zimo":{"l":2,"p":"m5"}},{"dapai":{"l":2,"p":"m1"}},{"zimo":{"l":3,"p":"z2"}},{"dapai":{"l":3,"p":"z2_"}},{"zimo":{"l":0,"p":"s9"}},{"dapai":{"l":0,"p":"s9_"}},{"zimo":{"l":1,"p":"s6"}},{"dapai":{"l":1,"p":"z5"}},{"zimo":{"l":2,"p":"p8"}},{"dapai":{"l":2,"p":"s3"}},{"zimo":{"l":3,"p":"z7"}},{"dapai":{"l":3,"p":"z7_"}},{"zimo":{"l":0,"p":"z4"}},{"dapai":{"l":0,"p":"z7"}},{"zimo":{"l":1,"p":"m8"}},{"dapai":{"l":1,"p":"z1"}},{"zimo":{"l":2,"p":"p2"}},{"dapai":{"l":2,"p":"p2_"}},{"zimo":{"l":3,"p":"m7"}},{"dapai":{"l":3,"p":"p2"}},{"zimo":{"l":0,"p":"m6"}},{"dapai":{"l":0,"p":"m6_"}},{"zimo":{"l":1,"p":"m9"}},{"dapai":{"l":1,"p":"z1"}},{"zimo":{"l":2,"p":"z6"}},{"dapai":{"l":2,"p":"z6_"}},{"zimo":{"l":3,"p":"p3"}},{"dapai":{"l":3,"p":"s1"}},{"zimo":{"l":0,"p":"z7"}},{"dapai":{"l":0,"p":"z7_"}},{"zimo":{"l":1,"p":"s5"}},{"dapai":{"l":1,"p":"m9"}},{"zimo":{"l":2,"p":"p1"}},{"dapai":{"l":2,"p":"s7"}},{"fulou":{"l":3,"m":"s7-89"}},{"dapai":{"l":3,"p":"s8"}},{"fulou":{"l":0,"m":"s888-"}},{"dapai":{"l":0,"p":"z4"}},{"zimo":{"l":1,"p":"p6"}},{"dapai":{"l":1,"p":"m4"}},{"zimo":{"l":2,"p":"m6"}},{"dapai":{"l":2,"p":"m9"}},{"zimo":{"l":3,"p":"z1"}},{"dapai":{"l":3,"p":"z1_"}},{"zimo":{"l":0,"p":"m2"}},{"dapai":{"l":0,"p":"z6"}},{"zimo":{"l":1,"p":"p9"}},{"dapai":{"l":1,"p":"p9_"}},{"zimo":{"l":2,"p":"p5"}},{"dapai":{"l":2,"p":"p1"}},{"zimo":{"l":3,"p":"s2"}},{"dapai":{"l":3,"p":"s2_"}},{"zimo":{"l":0,"p":"p6"}},{"dapai":{"l":0,"p":"p6_"}},{"zimo":{"l":1,"p":"p2"}},{"dapai":{"l":1,"p":"p5"}},{"zimo":{"l":2,"p":"m9"}},{"dapai":{"l":2,"p":"m9_"}},{"zimo":{"l":3,"p":"z3"}},{"dapai":{"l":3,"p":"z3_"}},{"zimo":{"l":0,"p":"s2"}},{"dapai":{"l":0,"p":"s2_"}},{"zimo":{"l":1,"p":"z1"}},{"dapai":{"l":1,"p":"z1_"}},{"zimo":{"l":2,"p":"z3"}},{"dapai":{"l":2,"p":"z3_"}},{"zimo":{"l":3,"p":"p1"}},{"dapai":{"l":3,"p":"p1_"}},{"zimo":{"l":0,"p":"m3"}},{"dapai":{"l":0,"p":"m3_"}},{"zimo":{"l":1,"p":"m7"}},{"dapai":{"l":1,"p":"m7_"}},{"zimo":{"l":2,"p":"s1"}},{"dapai":{"l":2,"p":"s1_"}},{"zimo":{"l":3,"p":"z4"}},{"dapai":{"l":3,"p":"z4_"}},{"zimo":{"l":0,"p":"s6"}},{"dapai":{"l":0,"p":"s6_"}},{"zimo":{"l":1,"p":"s7"}},{"dapai":{"l":1,"p":"p3"}},{"zimo":{"l":2,"p":"s2"}},{"dapai":{"l":2,"p":"p2"}},{"zimo":{"l":3,"p":"s5"}},{"dapai":{"l":3,"p":"s6"}},{"zimo":{"l":0,"p":"s7"}},{"dapai":{"l":0,"p":"s7_"}},{"zimo":{"l":1,"p":"p8"}},{"dapai":{"l":1,"p":"p8_"}},{"zimo":{"l":2,"p":"s9"}},{"dapai":{"l":2,"p":"s9_"}},{"zimo":{"l":3,"p":"s7"}},{"dapai":{"l":3,"p":"s7_"}},{"zimo":{"l":0,"p":"m3"}},{"dapai":{"l":0,"p":"m3_"}},{"zimo":{"l":1,"p":"p9"}},{"dapai":{"l":1,"p":"p9_"}},{"zimo":{"l":2,"p":"z3"}},{"dapai":{"l":2,"p":"z3_"}},{"zimo":{"l":3,"p":"s6"}},{"dapai":{"l":3,"p":"s6_"}},{"zimo":{"l":0,"p":"s1"}},{"dapai":{"l":0,"p":"s1_"}},{"zimo":{"l":1,"p":"m1"}},{"dapai":{"l":1,"p":"m1_"}},{"zimo":{"l":2,"p":"s4"}},{"dapai":{"l":2,"p":"s4_"}},{"zimo":{"l":3,"p":"z4"}},{"dapai":{"l":3,"p":"z4_"}},{"zimo":{"l":0,"p":"p7"}},{"dapai":{"l":0,"p":"p7_"}},{"hule":{"chongjia":0,"l":1,"shoupai":"m678p23456s33567p7_","zongfen":8,"fanzhong":[{"name_zh":"门前清","fenshu":2},{"name_zh":"断幺","fenshu":2},{"name_zh":"平和","fenshu":2},{"name_zh":"连六","fenshu":1},{"name_zh":"喜相逢","fenshu":1}],"fenpei":[-16,32,-8,-8]}}],
[{"qipai":{"quanfeng":3,"jushu":2,"zuoci":[3,2,1,0],"defen":[-18,-76,-70,164],"shoupai":["m11238p33447s1z15","m466p3688s124z135","m5579p699s147z234","m24789s2355669z7"]}},{"zimo":{"l":0,"p":"p8"}},{"dapai":{"l":0,"p":"z5"}},{"zimo":{"l":1,"p":"s4"}},{"dapai":{"l":1,"p":"z5"}},{"zimo":{"l":2,"p":"z1"}},{"dapai":{"l":2,"p":"p9"}},{"zimo":{"l":3,"p":"z5"}},{"dapai":{"l":3,"p":"z5_"}},{"zimo":{"l":0,"p":"z6"}},{"dapai":{"l":0,"p":"z6_"}},{"zimo":{"l":1,"p":"z7"}},{"dapai":{"l":1,"p":"z7_"}},{"zimo":{"l":2,"p":"z5"}},{"dapai":{"l":2,"p":"m9"}},{"zimo":{"l":3,"p":"p3"}},{"dapai":{"l":3,"p":"z7"}},{"zimo":{"l":0,"p":"s3"}},{"dapai":{"l":0,"p":"z1"}},{"zimo":{"l":1,"p":"s3"}},{"dapai":{"l":1,"p":"z1"}},{"zimo":{"l":2,"p":"m5"}},{"dapai":{"l":2,"p":"m7"}},{"zimo":{"l":3,"p":"z2"}},{"dapai":{"l":3,"p":"z2_"}},{"zimo":{"l":0,"p":"s8"}},{"dapai":{"l":0,"p":"m8"}},{"zimo":{"l":1,"p":"m8"}},{"dapai":{"l":1,"p":"z3"}},{"zimo":{"l":2,"p":"p5"}},{"dapai":{"l":2,"p":"m5"}},{"zimo":{"l":3,"p":"s2"}},{"dapai":{"l":3,"p":"s9"}},{"zimo":{"l":0,"p":"p9"}},{"dapai":{"l":0,"p":"s8"}},{"zimo":{"l":1,"p":"p9"}},{"dapai":{"l":1,"p":"p8"}},{"zimo":{"l":2,"p":"z6"}},{"dapai":{"l":2,"p":"m5"}},{"zimo":{"l":3,"p":"m2"}},{"dapai":{"l":3,"p":"m2"}},{"zimo":{"l":0,"p":"z3"}},{"dapai":{"l":0,"p":"z3_"}},{"zimo":{"l":1,"p":"p2"}},{"dapai":{"l":1,"p":"p6"}},{"zimo":{"l":2,"p":"s9"}},{"dapai":{"l":2,"p":"p5"}},{"zimo":{"l":3,"p":"s6"}},{"dapai":{"l":3,"p":"p3"}},{"zimo":{"l":0,"p":"z7"}},{"dapai":{"l":0,"p":"z7_"}},{"zimo":{"l":1,"p":"m7"}},{"dapai":{"l":1,"p":"p2"}},{"zimo":{"l":2,"p":"z4"}},{"dapai":{"l":2,"p":"s9"}},{"zimo":{"l":3,"p":"p1"}},{"dapai":{"l":3,"p":"p1_"}},{"zimo":{"l":0,"p":"s5"}},{"dapai":{"l":0,"p":"p3"}},{"zimo":{"l":1,"p":"z2"}},{"dapai":{"l":1,"p":"z2_"}},{"zimo":{"l":2,"p":"p2"}},{"dapai":{"l":2,"p":"p2_"}},{"zimo":{"l":3,"p":"m9"}},{"dapai":{"l":3,"p":"m2"}},{"zimo":{"l":0,"p":"z2"}},{"dapai":{"l":0,"p":"z2_"}},{"zimo":{"l":1,"p":"s8"}},{"dapai":{"l":1,"p":"s8_"}},{"zimo":{"l":2,"p":"s7"}},{"dapai":{"l":2,"p":"s7_"}},{"zimo":{"l":3,"p":"m4"}},{"dapai":{"l":3,"p":"m7"}},{"zimo":{"l":0,"p":"p2"}},{"dapai":{"l":0,"p":"m1"}},{"zimo":{"l":1,"p":"s8"}},{"dapai":{"l":1,"p":"s8_"}},{"zimo":{"l":2,"p":"s7"}},{"dapai":{"l":2,"p":"s7_"}},{"zimo":{"l":3,"p":"s4"}},{"dapai":{"l":3,"p":"m8"}},{"zimo":{"l":0,"p":"m4"}},{"dapai":{"l":0,"p":"m4_"}},{"fulou":{"l":3,"m":"m444+"}},{"dapai":{"l":3,"p":"s4"}},{"fulou":{"l":0,"m":"s34-5"}},{"dapai":{"l":0,"p":"s1"}},{"zimo":{"l":1,"p":"s7"}},{"dapai":{"l":1,"p":"s7_"}},{"zimo":{"l":2,"p":"p5"}},{"dapai":{"l":2,"p":"z4"}},{"zimo":{"l":3,"p":"s1"}},{"dapai":{"l":3,"p":"s1_"}},{"zimo":{"l":0,"p":"p4"}},{"hule":{"chongjia":null,"l":0,"shoupai":"m123p2344789p4,s34-5","zongfen":9,"fanzhong":[{"name_zh":"三色三步高","fenshu":6},{"name_zh":"平和","fenshu":2},{"name_zh":"自摸","fenshu":1}],"fenpei":[51,-17,-17,-17]}}],
[{"qipai":{"quanfeng":3,"jushu":3,"zuoci":[2,1,0,3],"defen":[-93,-87,147,33],"shoupai":["m8p6s1234789z1223","m1457p199s128z124","m689p3569s234z457","m1113p479s457z567"]}},{"zimo":{"l":0,"p":"z6"}},{"dapai":{"l":0,"p":"m8"}},{"zimo":{"l":1,"p":"z1"}},{"dapai":{"l":1,"p":"s8"}},{"zimo":{"l":2,"p":"m4"}},{"dapai":{"l":2,"p":"z4"}},{"zimo":{"l":3,"p":"s6"}},{"dapai":{"l":3,"p":"z7"}},{"zimo":{"l":0,"p":"m8"}},{"dapai":{"l":0,"p":"m8_"}},{"zimo":{"l":1,"p":"m2"}},{"dapai":{"l":1,"p":"m7"}},{"zimo":{"l":2,"p":"m9"}},{"dapai":{"l":2,"p":"z7"}},{"zimo":{"l":3,"p":"z6"}},{"dapai":{"l":3,"p":"z5"}},{"zimo":{"l":0,"p":"p4"}},{"dapai":{"l":0,"p":"z3"}},{"zimo":{"l":1,"p":"s7"}},{"dapai":{"l":1,"p":"s7_"}},{"zimo":{"l":2,"p":"p4"}},{"dapai":{"l":2,"p":"z5"}},{"zimo":{"l":3,"p":"m6"}},{"dapai":{"l":3,"p":"p4"}},{"zimo":{"l":0,"p":"p1"}},{"dapai":{"l":0,"p":"p1_"}},{"zimo":{"l":1,"p":"z3"}},{"dapai":{"l":1,"p":"z3_"}},{"zimo":{"l":2,"p":"m9"}},{"dapai":{"l":2,"p":"p9"}},{"fulou":{"l":1,"m":"p999+"}},{"dapai":{"l":1,"p":"m4"}},{"zimo":{"l":2,"p":"p3"}},{"dapai":{"l":2,"p":"p3_"}},{"zimo":{"l":3,"p":"p2"}},{"dapai":{"l":3,"p":"p2_"}},{"zimo":{"l":0,"p":"m7"}},{"dapai":{"l":0,"p":"m7_"}},{"zimo":{"l":1,"p":"z7"}},{"dapai":{"l":1,"p":"m5"}},{"fulou":{"l":2,"m":"m45-6"}},{"dapai":{"l":2,"p":"p6"}},{"zimo":{"l":3,"p":"s9"}},{"dapai":{"l":3,"p":"m6"}},{"zimo":{"l":0,"p":"z7"}},{"dapai":{"l":0,"p":"z7_"}},{"zimo":{"l":1,"p":"p8"}},{"dapai":{"l":1,"p":"z7"}},{"zimo":{"l":2,"p":"m9"}},{"dapai":{"l":2,"p":"m9_"}},{"zimo":{"l":3,"p":"p6"}},{"dapai":{"l":3,"p":"p6_"}},{"zimo":{"l":0,"p":"m2"}},{"dapai":{"l":0,"p":"m2_"}},{"zimo":{"l":1,"p":"z5"}},{"dapai":{"l":1,"p":"z5_"}},{"zimo":{"l":2,"p":"s4"}},{"dapai":{"l":2,"p":"s4_"}},{"zimo":{"l":3,"p":"p4"}},{"dapai":{"l":3,"p":"p4_"}},{"zimo":{"l":0,"p":"s6"}},{"dapai":{"l":0,"p":"z1"}},{"fulou":{"l":1,"m":"z111-"}},{"dapai":{"l":1,"p":"p8"}},{"zimo":{"l":2,"p":"m5"}},{"dapai":{"l":2,"p":"m5_"}},{"zimo":{"l":3,"p":"m3"}},{"dapai":{"l":3,"p":"s9"}},{"zimo":{"l":0,"p":"p2"}},{"dapai":{"l":0,"p":"z6"}},{"fulou":{"l":3,"m":"z666+"}},{"dapai":{"l":3,"p":"s7"}},{"zimo":{"l":0,"p":"m7"}},{"dapai":{"l":0,"p":"m7_"}},{"hule":{"chongjia":0,"l":2,"shoupai":"m8999p345s234m7_,m45-6","zongfen":9,"fanzhong":[{"name_zh":"三色三步高","fenshu":6},{"name_zh":"平和","fenshu":2},{"name_zh":"连六","fenshu":1}],"fenpei":[-17,-8,33,-8]}}]
],"defen":[180,-95,-110,25],"point":[4,2,1,3],"rank":[1,3,4,2]}
